candle/__init__.py
candle/candle_bus.py
candle/py.typed
candle/stress.py
python_can_candle-1.2.2.dist-info/licenses/LICENSE
python_can_candle-1.2.2.dist-info/METADATA
python_can_candle-1.2.2.dist-info/WHEEL
python_can_candle-1.2.2.dist-info/entry_points.txt
python_can_candle-1.2.2.dist-info/top_level.txt
python_can_candle-1.2.2.dist-info/RECORD
