Metadata-Version: 2.4
Name: python-can-candle
Version: 1.2.2
Summary: CAN driver for Geschwister Schneider USB/CAN devices
Author-email: Yu He <chinaheyu@outlook.com>
License:                   GNU LESSER GENERAL PUBLIC LICENSE
Project-URL: Homepage, https://github.com/chinaheyu/python-can-candle
Project-URL: Issues, https://github.com/chinaheyu/python-can-candle/issues
Keywords: gs_usb,can,candleLight
Requires-Python: >=3.8
License-File: LICENSE
Requires-Dist: python-can>=4.0.0
Requires-Dist: candle-api==0.0.9
Dynamic: license-file
